dave_rigging/__init__.cp312-win_amd64.pyd
dave_rigging/constants.cp312-win_amd64.pyd
dave_rigging/crane.cp312-win_amd64.pyd
dave_rigging/grommet_protector.cp312-win_amd64.pyd
dave_rigging/hoist.cp312-win_amd64.pyd
dave_rigging/liftingbeam.cp312-win_amd64.pyd
dave_rigging/liftpoint.cp312-win_amd64.pyd
dave_rigging/mixins.cp312-win_amd64.pyd
dave_rigging/quick_report.cp312-win_amd64.pyd
dave_rigging/register_nodeproperties.cp312-win_amd64.pyd
dave_rigging/rigging_analysis_node.cp312-win_amd64.pyd
dave_rigging/rigging_properties.cp312-win_amd64.pyd
dave_rigging/shackle.cp312-win_amd64.pyd
dave_rigging/sling_grommet.cp312-win_amd64.pyd
dave_rigging/sling_grommet_analysis_data.cp312-win_amd64.pyd
dave_rigging/types.cp312-win_amd64.pyd
dave_rigging/visual_painters.cp312-win_amd64.pyd
dave_rigging/gui/__init__.cp312-win_amd64.pyd
dave_rigging/gui/gui_friction_configuration.cp312-win_amd64.pyd
dave_rigging/gui/gui_integration.cp312-win_amd64.pyd
dave_rigging/gui/gui_optimizer.cp312-win_amd64.pyd
dave_rigging/gui/rigging_string_gui.cp312-win_amd64.pyd
dave_rigging/gui/rigging_system_creation_logic.cp312-win_amd64.pyd
dave_rigging/gui/thumbnail_maker.cp312-win_amd64.pyd
dave_rigging/gui/editors/__init__.cp312-win_amd64.pyd
dave_rigging/gui/editors/crane_node_editor.cp312-win_amd64.pyd
dave_rigging/gui/editors/grommet_mode_editor.cp312-win_amd64.pyd
dave_rigging/gui/editors/grommet_protector_editor.cp312-win_amd64.pyd
dave_rigging/gui/editors/hoist_node_editor.cp312-win_amd64.pyd
dave_rigging/gui/editors/lifting_beam_editor.cp312-win_amd64.pyd
dave_rigging/gui/editors/liftpoint_editor.cp312-win_amd64.pyd
dave_rigging/gui/editors/rigging_analysis_editor.cp312-win_amd64.pyd
dave_rigging/gui/editors/rigging_string_edit_window.cp312-win_amd64.pyd
dave_rigging/gui/editors/rigging_string_node_editor.cp312-win_amd64.pyd
dave_rigging/gui/editors/shackle_editor.cp312-win_amd64.pyd
dave_rigging/gui/editors/sling_grommet_editor.cp312-win_amd64.pyd
dave_rigging-2025.0.8.dist-info/licenses/LICENSE.txt
dave_rigging-2025.0.8.dist-info/METADATA
dave_rigging-2025.0.8.dist-info/WHEEL
dave_rigging-2025.0.8.dist-info/top_level.txt
dave_rigging-2025.0.8.dist-info/RECORD
